conditional-drawdown/__init__.py
conditional-drawdown/drawdown.py
conditional_drawdown/__init__.py
conditional_drawdown/drawdown.py
tests/__init__.py
conditional_drawdown-0.1.1.dist-info/LICENSE
conditional_drawdown-0.1.1.dist-info/METADATA
conditional_drawdown-0.1.1.dist-info/WHEEL
conditional_drawdown-0.1.1.dist-info/top_level.txt
conditional_drawdown-0.1.1.dist-info/RECORD
