Metadata-Version: 2.1
Name: conditional_drawdown
Version: 0.1.1
Summary: A Python library for drawdown risk analysis with Conditional Expected Drawdown (CED).
Home-page: https://github.com/internQuant/conditional-drawdown
Author: internQuant
Author-email: interQuant <cinzeis-rehang.0l@icloud.com>
License: MIT
Keywords: finance,drawdown,risk,portfolio,CED
Classifier: Development Status :: 3 - Alpha
Classifier: Intended Audience :: Financial and Insurance Industry
Classifier: Programming Language :: Python :: 3
Classifier: License :: OSI Approved :: MIT License
Requires-Python: >=3.9
License-File: LICENSE
Requires-Dist: numpy
Requires-Dist: pandas
Requires-Dist: numba
Requires-Dist: yfinance
